Workbook

Sheet 📋 Vue d'ensemble
A1: Référentiel d'accompagnement DevOps
A2: 205 actions d'accompagnement réparties sur 8 axes et 43 questions
A4: Stats globales
A5: Total actions | B5: =COUNTA('🎯 205 Actions'!A2:A300)-COUNTBLANK('🎯 205 Actions'!A2:A300) -> 111
A6: Questions couvertes | B6: =SUMPRODUCT(1/COUNTIF('🎯 205 Actions'!B2:B206,'🎯 205 Actions'!B2:B206)) -> 43
A7: Axes couverts | B7: =SUMPRODUCT(1/COUNTIF('🎯 205 Actions'!C2:C206,'🎯 205 Actions'!C2:C206)) -> 8
A8: Ateliers à écrire | B8: =COUNTIF('🎯 205 Actions'!K2:K206,"À écrire") -> 205
A9: Ateliers écrits | B9: =COUNTIF('🎯 205 Actions'!K2:K206,"Écrit") -> 0
A10: % Avancement | B10: =IFERROR(B9/B5,0) -> 0
A12: Comment lire ce référentiel
A13: Onglet 🎯 205 Actions | B13: Catalogue complet de toutes les actions, filtrable et triable.
A14: Onglet 📊 Par axe | B14: Synthèse par axe — combien d'actions, combien d'ateliers écrits.
A15: Onglet 🚦 Par priorité | B15: Vue par priorité (Haute/Moyenne/Basse/Préalable) pour planifier.
A16: Onglet 📝 Backlog Phase 1 | B16: Top 30-50 actions à écrire en priorité (à remplir avec données LCL).
A18: Statut 'À écrire' | B18: Atelier pas encore rédigé.
A19: Statut 'En cours' | B19: Atelier en rédaction (mets ton nom dans 'Assigné').
A20: Statut 'Écrit' | B20: Atelier rédigé, prêt pour review.
A21: Statut 'Validé' | B21: Atelier reviewé et publié.

Sheet 🎯 205 Actions
A1: # | B1: Question ID | C1: Axe | D1: Question | E1: Type | F1: Niveau | G1: Priorité | H1: Titre du niveau | I1: Action | J1: Métrique GitLab | K1: Statut atelier | L1: Assigné | M1: Notes | N1: Verdict coach | O1: Avis coach | P1: Action optimale ? (coach) | Q1: Ordre de production (coach)
A2: 1 | B2: C01 | C2: Culture & Rituels | D2: La squad dispose-t-elle de rituels communs entre Dev, Ops et autres parties prenantes ? | E2: Atelier | F2: Initial 🔴 | G2: Haute | H2: Aucun rituel commun | I2: Atelier "Notre premier daily" : accompagner la squad à instaurer un daily standup de 15 min max avec Dev + Ops | J2: — | K2: À écrire | N2: ✓ Bon | O2: Sensibilisation + 1er geste concret : gradation cohérente avec le niveau. | P2: 🔁 Daily défendable, mais pour une squad sans aucun rituel, tenter d'abord une rétro blameless : construit le muscle de collaboration et fait remonter la douleur (le daily glisse vite vers le statut). À jauger selon la maturité relationnelle. | Q2: V4 · Rituels communs Dev/Ops
A3: 2 | B3: C01 | C3: Culture & Rituels | D3: La squad dispose-t-elle de rituels communs entre Dev, Ops et autres parties prenantes ? | E3: Atelier | F3: Initial 🔴 | G3: Haute | H3: Aucun rituel commun | I3: Session "Pourquoi des rituels ?" : faire comprendre ensemble la valeur des rituels comme ciment de la collaboration | J3: — | K3: À écrire | N3: ✓ Bon | O3: Sensibilisation + 1er geste concret : gradation cohérente avec le niveau. | P3: 👍 Oui — bonne intervention pour ce palier, je ne changerais pas. | Q3: V4 · Rituels communs Dev/Ops
A4: 3 | B4: C01 | C4: Culture & Rituels | D4: La squad dispose-t-elle de rituels communs entre Dev, Ops et autres parties prenantes ? | E4: Atelier | F4: En Progrès 🟡 | G4: Moyenne | H4: Rituels naissants mais irréguliers | I4: Session formalisation des rituels : bloquer des créneaux fixes dans les agendas et co-construire un format standard | J4: — | K4: À écrire | N4: ✓ Bon | O4: Passage à la systématisation : logique de progression respectée. | P4: 👍 Oui — bonne intervention pour ce palier, je ne changerais pas. | Q4: V4 · Rituels communs Dev/Ops
A5: 4 | B5: C01 | C5: Culture & Rituels | D5: La squad dispose-t-elle de rituels communs entre Dev, Ops et autres parties prenantes ? | E5: Atelier | F5: En Progrès 🟡 | G5: Moyenne | H5: Rituels naissants mais irréguliers | I5: Atelier inclusion des parties prenantes : élargir progressivement les rituels à QA, sécu, produit | J5: — | K5: À écrire | N5: ✓ Bon | O5: Passage à la systématisation : logique de progression respectée. | P5: 👍 Oui — bonne intervention pour ce palier, je ne changerais pas. | Q5: V4 · Rituels communs Dev/Ops
A6: 5 | B6: C01 | C6: Culture & Rituels | D6: La squad dispose-t-elle de rituels communs entre Dev, Ops et autres parties prenantes ? | E6: Atelier | F6: Formalisé 🔵 | G6: Basse | H6: Rituels en place mais pas toutes les parties prenantes | I6: Session mesure de l'efficacité : co-évaluer si les blocages remontés en daily sont résolus dans la journée et ajuster le format | J6: — | K6: À écrire | N6: ✓ Bon | O6: Consolidation/mesure : clôt proprement le gradient de maturité. | P6: 👍 Oui — bonne intervention pour ce palier, je ne changerais pas. | Q6: V4 · Rituels communs Dev/Ops
A7: 6 | B7: C02 | C7: Culture & Rituels | D7: Les outils collaboratifs (Teams, Jira, Confluence) sont-ils utilisés efficacement pour réduire les frictions ? | E7: Atelier | F7: Initial 🔴 | G7: Haute | H7: Outils utilisés de façon chaotique | I7: Atelier "Notre inventaire outillage" : lister ensemble tous les outils utilisés, identifier les doublons et les usages qui se chevauchent | J7: — | K7: À écrire | N7: ✓ Bon | O7: Sensibilisation + 1er geste concret : gradation cohérente avec le niveau. | P7: 👍 Oui — bonne intervention pour ce palier, je ne changerais pas. | Q7: V4 · Outils collaboratifs
A8: 7 | B8: C02 | C8: Culture & Rituels | D8: Les outils collaboratifs (Teams, Jira, Confluence) sont-ils utilisés efficacement pour réduire les frictions ? | E8: Atelier | F8: Initial 🔴 | G8: Haute | H8: Outils utilisés de façon chaotique | I8: Session "Un outil, un usage" : co-décider des conventions — quel outil pour quel usage | J8: — | K8: À écrire | N8: ✓ Bon | O8: Sensibilisation + 1er geste concret : gradation cohérente avec le niveau. | P8: 👍 Oui — bonne intervention pour ce palier, je ne changerais pas. | Q8: V4 · Outils collaboratifs
A9: 8 | B9: C02 | C9: Culture & Rituels | D9: Les outils collaboratifs (Teams, Jira, Confluence) sont-ils utilisés efficacement pour réduire les frictions ? | E9: Atelier | F9: En Progrès 🟡 | G9: Moyenne | H9: Outils identifiés mais pas de conventions | I9: Session documentation des conventions : formaliser en 1 page les règles d'usage et les partager avec toute la squad | J9: — | K9: À écrire | N9: ✓ Bon | O9: Passage à la systématisation : logique de progression respectée. | P9: 👍 Oui — bonne intervention pour ce palier, je ne changerais pas. | Q9: V4 · Outils collaboratifs
A10: 9 | B10: C02 | C10: Culture & Rituels | D10: Les outils collaboratifs (Teams, Jira, Confluence) sont-ils utilisés efficacement pour réduire les frictions ? | E10: Atelier | F10: En Progrès 🟡 | G10: Moyenne | H10: Outils identifiés mais pas de conventions | I10: Atelier audit d'adoption : identifier qui utilise quoi et former les récalcitrants | J10: — | K10: À écrire | N10: ✓ Bon | O10: Passage à la systématisation : logique de progression respectée. | P10: 🔁 Reformuler « former les récalcitrants » → « comprendre pourquoi l'adoption coince ». L'adoption partielle = rarement mauvaise volonté, souvent inadéquation outil/workflow. | Q10: V4 · Outils collaboratifs
A11: 10 | B11: C02 | C11: Culture & Rituels | D11: Les outils collaboratifs (Teams, Jira, Confluence) sont-ils utilisés efficacement pour réduire les frictions ? | E11: Atelier | F11: Formalisé 🔵 | G11: Basse | H11: Conventions définies mais adoption partielle | I11: Session automatisation : mettre en place les notifications croisées, les liens automatiques entre outils et les templates | J11: — | K11: À écrire | N11: ✓ Bon | O11: Consolidation/mesure : clôt proprement le gradient de maturité. | P11: 👍 Oui — bonne intervention pour ce palier, je ne changerais pas. | Q11: V4 · Outils collaboratifs
A12: 11 | B12: C03 | C12: Culture & Rituels | D12: Les informations critiques (problèmes, priorités, décisions) circulent-elles rapidement et clairement à tous les membres ? | E12: Atelier | F12: Initial 🔴 | G12: Haute | H12: Les infos critiques arrivent tard ou pas du tout | I12: Atelier "Notre canal incidents" : créer ensemble un canal dédié aux incidents avec un template de communication standard | J12: — | K12: À écrire | N12: ✓ Bon | O12: Sensibilisation + 1er geste concret : gradation cohérente avec le niveau. | P12: 👍 Oui — bonne intervention pour ce palier, je ne changerais pas. | Q12: V4 · Circulation des infos critiques
A13: 12 | B13: C03 | C13: Culture & Rituels | D13: Les informations critiques (problèmes, priorités, décisions) circulent-elles rapidement et clairement à tous les membres ? | E13: Atelier | F13: Initial 🔴 | G13: Haute | H13: Les infos critiques arrivent tard ou pas du tout | I13: Session "Quand et comment communiquer ?" : co-construire un protocole de communication de crise adapté à la squad | J13: — | K13: À écrire | N13: ✓ Bon | O13: Sensibilisation + 1er geste concret : gradation cohérente avec le niveau. | P13: 👍 Oui — bonne intervention pour ce palier, je ne changerais pas. | Q13: V4 · Circulation des infos critiques
... A206: 205 | B206: X05 | C206: Sécurité | D206: Approbations invalidées après un nouveau push | E206: Sécurité | F206: — | G206: Haute | H206: — | I206: Mise en conformité sécurité : activation du setting obligatoire — Remove all approvals when commits are added | J206: — | K206: À écrire | N206: ⚠ Doublon | O206: « Reset approvals on push » est mot pour mot l'action Q02-141. Doublon exact. | P206: ➖ Item de conformité : geste correct mais redondant avec H03/Q02 (cf. colonne Verdict). | Q206: V1 · Runbook GitLab hardening

Sheet MPE
A1: # | B1: Question ID | C1: Axe | D1: Question | E1: Niveau | F1: Priorité | G1: Action | H1: Remarques MPE | I1: Ordre de production | J1: Besoin déjà couvert ? | K1: Documentation existante
A2: 1 | B2: C01 | C2: Culture & Rituels | D2: La squad dispose-t-elle de rituels communs entre Dev, Ops et autres parties prenantes ? | E2: Initial 🔴 | F2: Haute | G2: Atelier "Notre premier daily" : accompagner la squad à instaurer un daily standup de 15 min max avec Dev + Ops | H2: 🔁 Daily défendable, mais pour une squad sans aucun rituel, tenter d'abord une rétro blameless : construit le muscle de collaboration et fait remonter la douleur (le daily glisse vite vers le statut). À jauger selon la maturité relationnelle. | I2: V4 · Rituels communs Dev/Ops | J2: oui | K2: 💊 Comment intégrer les Ops aux rituels agiles
A3: 2 | B3: C01 | C3: Culture & Rituels | D3: La squad dispose-t-elle de rituels communs entre Dev, Ops et autres parties prenantes ? | E3: Initial 🔴 | F3: Haute | G3: Session "Pourquoi des rituels ?" : faire comprendre ensemble la valeur des rituels comme ciment de la collaboration | H3: ok | I3: V4 · Rituels communs Dev/Ops | J3: oui | K3: 💊 Comment intégrer les Ops aux rituels agiles
A4: 3 | B4: C01 | C4: Culture & Rituels | D4: La squad dispose-t-elle de rituels communs entre Dev, Ops et autres parties prenantes ? | E4: En Progrès 🟡 | F4: Moyenne | G4: Session formalisation des rituels : bloquer des créneaux fixes dans les agendas et co-construire un format standard | H4: ok | I4: V4 · Rituels communs Dev/Ops | J4: oui | K4: 💊 Comment intégrer les Ops aux rituels agiles
A5: 4 | B5: C01 | C5: Culture & Rituels | D5: La squad dispose-t-elle de rituels communs entre Dev, Ops et autres parties prenantes ? | E5: En Progrès 🟡 | F5: Moyenne | G5: Atelier inclusion des parties prenantes : élargir progressivement les rituels à QA, sécu, produit | H5: ok | I5: V4 · Rituels communs Dev/Ops | J5: oui | K5: 💊 Comment intégrer les Ops aux rituels agiles
A6: 5 | B6: C01 | C6: Culture & Rituels | D6: La squad dispose-t-elle de rituels communs entre Dev, Ops et autres parties prenantes ? | E6: Formalisé 🔵 | F6: Basse | G6: Session mesure de l'efficacité : co-évaluer si les blocages remontés en daily sont résolus dans la journée et ajuster le format | H6: ok | I6: V4 · Rituels communs Dev/Ops | J6: oui | K6: 💊 Comment intégrer les Ops aux rituels agiles
A7: 6 | B7: C02 | C7: Culture & Rituels | D7: Les outils collaboratifs (Teams, Jira, Confluence) sont-ils utilisés efficacement pour réduire les frictions ? | E7: Initial 🔴 | F7: Haute | G7: Atelier "Notre inventaire outillage" : lister ensemble tous les outils utilisés, identifier les doublons et les usages qui se chevauchent | H7: ok | I7: V4 · Outils collaboratifs | J7: oui
A8: 7 | B8: C02 | C8: Culture & Rituels | D8: Les outils collaboratifs (Teams, Jira, Confluence) sont-ils utilisés efficacement pour réduire les frictions ? | E8: Initial 🔴 | F8: Haute | G8: Session "Un outil, un usage" : co-décider des conventions — quel outil pour quel usage | H8: ok | I8: V4 · Outils collaboratifs | J8: oui
A9: 8 | B9: C02 | C9: Culture & Rituels | D9: Les outils collaboratifs (Teams, Jira, Confluence) sont-ils utilisés efficacement pour réduire les frictions ? | E9: En Progrès 🟡 | F9: Moyenne | G9: Session documentation des conventions : formaliser en 1 page les règles d'usage et les partager avec toute la squad | H9: ok | I9: V4 · Outils collaboratifs | J9: oui
A10: 9 | B10: C02 | C10: Culture & Rituels | D10: Les outils collaboratifs (Teams, Jira, Confluence) sont-ils utilisés efficacement pour réduire les frictions ? | E10: En Progrès 🟡 | F10: Moyenne | G10: Atelier audit d'adoption : identifier qui utilise quoi et former les récalcitrants | H10: 🔁 Reformuler « former les récalcitrants » → « comprendre pourquoi l'adoption coince ». L'adoption partielle = rarement mauvaise volonté, souvent inadéquation outil/workflow. | I10: V4 · Outils collaboratifs | J10: oui
A11: 10 | B11: C02 | C11: Culture & Rituels | D11: Les outils collaboratifs (Teams, Jira, Confluence) sont-ils utilisés efficacement pour réduire les frictions ? | E11: Formalisé 🔵 | F11: Basse | G11: Session automatisation : mettre en place les notifications croisées, les liens automatiques entre outils et les templates | H11: ok | I11: V4 · Outils collaboratifs | J11: oui
A12: 11 | B12: C03 | C12: Culture & Rituels | D12: Les informations critiques (problèmes, priorités, décisions) circulent-elles rapidement et clairement à tous les membres ? | E12: Initial 🔴 | F12: Haute | G12: Atelier "Notre canal incidents" : créer ensemble un canal dédié aux incidents avec un template de communication standard | H12: ok | I12: V4 · Circulation des infos critiques | J12: oui
A13: 12 | B13: C03 | C13: Culture & Rituels | D13: Les informations critiques (problèmes, priorités, décisions) circulent-elles rapidement et clairement à tous les membres ? | E13: Initial 🔴 | F13: Haute | G13: Session "Quand et comment communiquer ?" : co-construire un protocole de communication de crise adapté à la squad | H13: ok | I13: V4 · Circulation des infos critiques | J13: oui
A14: 13 | B14: C03 | C14: Culture & Rituels | D14: Les informations critiques (problèmes, priorités, décisions) circulent-elles rapidement et clairement à tous les membres ? | E14: En Progrès 🟡 | F14: Moyenne | G14: Session template d'incident : formaliser ensemble le format — quoi, impact, qui gère, ETA — et l'imposer comme standard | H14: ok | I14: V4 · Circulation des infos critiques | J14: oui
A15: 14 | B15: C03 | C15: Culture & Rituels | D15: Les informations critiques (problèmes, priorités, décisions) circulent-elles rapidement et clairement à tous les membres ? | E15: En Progrès 🟡 | F15: Moyenne | G15: Atelier proactivité : instaurer un point hebdo de 5 min sur les risques identifiés et les dépendances à venir | H15: ok | I15: V4 · Circulation des infos critiques | J15: oui
A16: 15 | B16: C03 | C16: Culture & Rituels | D16: Les informations critiques (problèmes, priorités, décisions) circulent-elles rapidement et clairement à tous les membres ? | E16: Formalisé 🔵 | F16: Basse | G16: Session "Angles morts" : identifier ensemble qui ne reçoit pas les infos — nouveaux, mi-temps, externes — et les inclure | H16: ok | I16: V4 · Circulation des infos critiques | J16: oui
A17: 16 | B17: C04 | C17: Culture & Rituels | D17: Les rôles et responsabilités sont-ils bien compris et partagés entre les parties ? | E17: Initial 🔴 | F17: Haute | G17: Atelier RACI : co-construire ensemble une matrice RACI sur les 10 activités clés de la squad en 30 min | H17: ✎ Reformuler — « co-construire ensemble » = pléonasme (co = ensemble). Sinon atelier RACI 30 min : excellent format. 🔁 RACI finit souvent en théâtre affiché jamais relu. Pour une squad : delegation poker (Management 3.0) ou journal de décisions d'abord — plus engageant et collant. RACI en repli. | I17: V4 · Rôles & responsabilités (RACI/delegation) | J17: oui
A18: 17 | B18: C04 | C18: Culture & Rituels | D18: Les rôles et responsabilités sont-ils bien compris et partagés entre les parties ? | E18: Initial 🔴 | F18: Haute | G18: Session "Qui décide quoi ?" : clarifier les décisions clés — qui valide un merge, qui contacte le support N3 | H18: ok | I18: V4 · Rôles & responsabilités (RACI/delegation) | J18: oui
... A21: 20 | B21: C04 | C21: Culture & Rituels | D21: Les rôles et responsabilités sont-ils bien compris et partagés entre les parties ? | E21: Formalisé 🔵 | F21: Basse | G21: Session revue trimestrielle : instaurer une revue de la RACI à chaque changement d'équipe ou de périmètre | H21: ok | I21: V4 · Rôles & responsabilités (RACI/delegation) | J21: oui
A22: 21 | B22: C05 | C22: Culture & Rituels | D22: Le backlog intègre-t-il les besoins techniques et opérationnels ? (→ User Stories Dev, Sec ET Ops) | E22: Initial 🔴 | F22: Haute | G22: Atelier "Notre backlog est-il complet ?" : faire émerger ce qui manque côté technique, sécu et ops | H22: ok | I22: V5 · Backlog technique & ops | J22: oui | K22: 💊 Users Stories Dev + Ops
A23: 22 | B23: C05 | C23: Culture & Rituels | D23: Le backlog intègre-t-il les besoins techniques et opérationnels ? (→ User Stories Dev, Sec ET Ops) | E23: Initial 🔴 | F23: Haute | G23: Session négociation avec le PO : accompagner la squad à défendre un quota minimum de 20% pour le technique | H23: ok | I23: V5 · Backlog technique & ops | J23: oui | K23: 💊 Users Stories Dev + Ops
A24: 23 | B24: C05 | C24: Culture & Rituels | D24: Le backlog intègre-t-il les besoins techniques et opérationnels ? (→ User Stories Dev, Sec ET Ops) | E24: En Progrès 🟡 | F24: Moyenne | G24: Session quota technique : formaliser un engagement de 20% minimum par sprint, non négociable | H24: 🔁 Quota fixe « non négociable » = dogmatique, se retourne contre l'équipe. Relier l'investissement technique au RISQUE observé (incidents, lead time, CVE) pour que le PO arbitre sur des faits. Le quota comme repère, pas comme règle. | I24: V5 · Backlog technique & ops | J24: oui | K24: 💊 Users Stories Dev + Ops
A25: 24 | B25: C05 | C25: Culture & Rituels | D25: Le backlog intègre-t-il les besoins techniques et opérationnels ? (→ User Stories Dev, Sec ET Ops) | E25: En Progrès 🟡 | F25: Moyenne | G25: Atelier "US techniques bien rédigées" : apprendre à écrire des US techniques avec de la valeur visible pour le PO | H25: ok | I25: V5 · Backlog technique & ops | J25: oui | K25: 💊 Users Stories Dev + Ops
A26: 25 | B26: C05 | C26: Culture & Rituels | D26: Le backlog intègre-t-il les besoins techniques et opérationnels ? (→ User Stories Dev, Sec ET Ops) | E26: Formalisé 🔵 | F26: Basse | G26: Session élargissement du backlog : intégrer systématiquement les sujets sécu (scan, dépendances) et ops (monitoring, alerting) | H26: ok | I26: V5 · Backlog technique & ops | J26: oui | K26: 💊 Users Stories Dev + Ops
A27: 26 | B27: C06 | C27: Culture & Rituels | D27: Les dépendances avec d'autres squads sont-elles anticipées et coordonnées sans blocage ? | E27: Initial 🔴 | F27: Haute | G27: Atelier cartographie des dépendances : identifier ensemble toutes les dépendances externes et les rendre visibles | H27: ok | I27: V5 · Dépendances inter-squads | J27: oui
A28: 27 | B28: C06 | C28: Culture & Rituels | D28: Les dépendances avec d'autres squads sont-elles anticipées et coordonnées sans blocage ? | E28: Initial 🔴 | F28: Haute | G28: Session synchro inter-squads : instaurer un point bimensuel de 15 min avec les squads dont on dépend | H28: ok | I28: V5 · Dépendances inter-squads | J28: oui
A29: 28 | B29: C06 | C29: Culture & Rituels | D29: Les dépendances avec d'autres squads sont-elles anticipées et coordonnées sans blocage ? | E29: En Progrès 🟡 | F29: Moyenne | G29: Session intégration au sprint planning : pour chaque US, identifier "de qui dépend-on ?" et traiter les flous comme des risques | H29: ok | I29: V5 · Dépendances inter-squads | J29: oui
A30: 29 | B30: C06 | C30: Culture & Rituels | D30: Les dépendances avec d'autres squads sont-elles anticipées et coordonnées sans blocage ? | E30: En Progrès 🟡 | F30: Moyenne | G30: Atelier SLA de réponse : négocier ensemble des engagements de réponse avec les squads dépendantes | H30: 🔁 SLA inter-squads sans autorité = rarement tenus. Préférer working agreements + dépendances visibles sur board partagé (PI planning allégé) à un SLA lettre morte. | I30: V5 · Dépendances inter-squads | J30: oui
A31: 30 | B31: C06 | C31: Culture & Rituels | D31: Les dépendances avec d'autres squads sont-elles anticipées et coordonnées sans blocage ? | E31: Formalisé 🔵 | F31: Basse | G31: Session contrats d'interface : documenter ensemble les interfaces exposées pour que les autres squads puissent s'y fier | H31: ok | I31: V5 · Dépendances inter-squads | J31: oui
A32: 31 | B32: C07 | C32: Culture & Rituels | D32: Avez-vous instauré des DevOps Reviews régulières ? (avec actions concrètes prises et réalisées) | E32: Initial 🔴 | F32: Haute | G32: Accompagnement DevOps Review : co-construire le format, le rythme et les indicateurs de la première DevOps Review | H32: ok | I32: V1 · Canevas DevOps Review | J32: oui
A33: 32 | B33: C07 | C33: Culture & Rituels | D33: Avez-vous instauré des DevOps Reviews régulières ? (avec actions concrètes prises et réalisées) | E33: Initial 🔴 | F33: Haute | G33: Session "Notre première DevOps Review" : animer ensemble la première session et poser 3 actions concrètes pour le mois suivant | H33: ok | I33: V1 · Canevas DevOps Review | J33: oui
A34: 33 | B34: C07 | C34: Culture & Rituels | D34: Avez-vous instauré des DevOps Reviews régulières ? (avec actions concrètes prises et réalisées) | E34: En Progrès 🟡 | F34: Moyenne | G34: Session formalisation du template : métriques clés, incidents marquants, actions passées, prochaines actions | H34: ok | I34: V1 · Canevas DevOps Review | J34: oui
A35: 34 | B35: C07 | C35: Culture & Rituels | D35: Avez-vous instauré des DevOps Reviews régulières ? (avec actions concrètes prises et réalisées) | E35: En Progrès 🟡 | F35: Moyenne | G35: Atelier suivi des actions : chaque action a un responsable et une deadline — on commence à la prochaine session | H35: ok | I35: V1 · Canevas DevOps Review | J35: oui
A36: 35 | B36: C07 | C36: Culture & Rituels | D36: Avez-vous instauré des DevOps Reviews régulières ? (avec actions concrètes prises et réalisées) | E36: Formalisé 🔵 | F36: Basse | G36: Session ouverture au management : préparer ensemble une DevOps Review pour le management — métriques, progrès, blocages | H36: ok | I36: V1 · Canevas DevOps Review | J36: oui
A37: 36 | B37: C08 | C37: Culture & Rituels | D37: Vous sentez-vous libre de partager des idées, signaler des problèmes ou admettre des erreurs sans crainte de répercussions ? | E37: Initial 🔴 | F37: Haute | G37: Atelier blameless culture : introduire le post-mortem sans blame sur un incident récent — zéro nom, que le système | H37: ok | I37: V1 · Atelier Blameless / Sécurité psy | J37: oui | K37: 💊 Post Mortem ; 🖼️ Template - Post Mortem
A38: 37 | B38: C08 | C38: Culture & Rituels | D38: Vous sentez-vous libre de partager des idées, signaler des problèmes ou admettre des erreurs sans crainte de répercussions ? | E38: Initial 🔴 | F38: Haute | G38: Session "On parle du système, jamais des gens" : ancrer la règle et la pratiquer ensemble sur un cas concret | H38: ok | I38: V1 · Atelier Blameless / Sécurité psy | J38: oui | K38: 💊 Post Mortem ; 🖼️ Template - Post Mortem
A39: 38 | B39: C08 | C39: Culture & Rituels | D39: Vous sentez-vous libre de partager des idées, signaler des problèmes ou admettre des erreurs sans crainte de répercussions ? | E39: En Progrès 🟡 | F39: Moyenne | G39: Atelier valorisation publique : apprendre à remercier explicitement celui qui remonte un problème | H39: ok | I39: V1 · Atelier Blameless / Sécurité psy | J39: oui | K39: 💊 Post Mortem ; 🖼️ Template - Post Mortem
A40: 39 | B40: C08 | C40: Culture & Rituels | D40: Vous sentez-vous libre de partager des idées, signaler des problèmes ou admettre des erreurs sans crainte de répercussions ? | E40: En Progrès 🟡 | F40: Moyenne | G40: Session rétrospective anonyme : utiliser des formats anonymes pour vérifier que tout le monde se sent vraiment libre | H40: 🔁 Rétro anonyme = béquille de diagnostic utile, mais pas un régime permanent (signale une sécurité psy basse). À utiliser temporairement, viser le non-anonyme. | I40: V1 · Atelier Blameless / Sécurité psy | J40: oui | K40: 💊 Post Mortem ; 🖼️ Template - Post Mortem
A41: 40 | B41: C08 | C41: Culture & Rituels | D41: Vous sentez-vous libre de partager des idées, signaler des problèmes ou admettre des erreurs sans crainte de répercussions ? | E41: Formalisé 🔵 | F41: Basse | G41: Session extension de la sécurité psychologique : travailler la posture dans les interactions inter-squads et avec le management | H41: ok | I41: V1 · Atelier Blameless / Sécurité psy | J41: oui | K41: 💊 Post Mortem ; 🖼️ Template - Post Mortem
A42: 41 | B42: C09 | C42: Culture & Rituels | D42: La squad partage-t-elle ses retours d'expérience avec d'autres équipes internes ou externes ? | E42: Initial 🔴 | F42: Haute | G42: Session "Notre premier lightning talk" : identifier un sujet maîtrisé et préparer ensemble un talk de 10 min pour une squad voisine | H42: ok | I42: V5 · Partage des REX | J42: oui | K42: 💊 Post Mortem
A43: 42 | B43: C09 | C43: Culture & Rituels | D43: La squad partage-t-elle ses retours d'expérience avec d'autres équipes internes ou externes ? | E43: Initial 🔴 | F43: Haute | G43: Atelier "Qu'est-ce qu'on sait faire ?" : faire émerger les expertises de la squad qui pourraient intéresser d'autres équipes | H43: ok | I43: V5 · Partage des REX | J43: oui | K43: 💊 Post Mortem
A44: 43 | B44: C09 | C44: Culture & Rituels | D44: La squad partage-t-elle ses retours d'expérience avec d'autres équipes internes ou externes ? | E44: En Progrès 🟡 | F44: Moyenne | G44: Session REX trimestriel : planifier ensemble un format court et l'inscrire dans le calendrier | H44: ok | I44: V5 · Partage des REX | J44: oui | K44: 💊 Post Mortem
A45: 44 | B45: C09 | C45: Culture & Rituels | D45: La squad partage-t-elle ses retours d'expérience avec d'autres équipes internes ou externes ? | E45: En Progrès 🟡 | F45: Moyenne | G45: Atelier documentation du savoir : publier un résumé des REX sur Confluence pour élargir l'audience | H45: ok | I45: V5 · Partage des REX | J45: oui | K45: 💊 Post Mortem
A46: 45 | B46: C09 | C46: Culture & Rituels | D46: La squad partage-t-elle ses retours d'expérience avec d'autres équipes internes ou externes ? | E46: Formalisé 🔵 | F46: Basse | G46: Session élargissement de l'audience : inviter d'autres tribus et co-construire un format bidirectionnel d'échange | H46: ok | I46: V5 · Partage des REX | J46: oui | K46: 💊 Post Mortem
A47: 46 | B47: C10 | C47: Culture & Rituels | D47: Êtes-vous maître de votre calendrier de livraison (hors frozen zone) ? | E47: Initial 🔴 | F47: Haute | G47: Atelier "Nos contraintes dans le miroir" : lister ensemble tout ce qui empêche de livrer quand on veut | H47: ✎ Style — « dans le miroir » : bon, mais le motif revient ~10× dans le catalogue. Varier pour les squads qui enchaînent plusieurs ateliers. | I47: V5 · Maîtrise du calendrier de livraison | J47: oui
A48: 47 | B48: C10 | C48: Culture & Rituels | D48: Êtes-vous maître de votre calendrier de livraison (hors frozen zone) ? | E48: Initial 🔴 | F48: Haute | G48: Session négociation des SLA : pour chaque contrainte externe, demander un SLA ou un process de fast-track | H48: ok | I48: V5 · Maîtrise du calendrier de livraison | J48: oui
A49: 48 | B49: C10 | C49: Culture & Rituels | D49: Êtes-vous maître de votre calendrier de livraison (hors frozen zone) ? | E49: En Progrès 🟡 | F49: Moyenne | G49: Atelier automatisation des validations : identifier les validations manuelles qui peuvent être automatisées | H49: ok | I49: V5 · Maîtrise du calendrier de livraison | J49: oui
A50: 49 | B50: C10 | C50: Culture & Rituels | D50: Êtes-vous maître de votre calendrier de livraison (hors frozen zone) ? | E50: En Progrès 🟡 | F50: Moyenne | G50: Session workarounds documentés : formaliser les contournements pour les contraintes incompressibles | H50: ok | I50: V5 · Maîtrise du calendrier de livraison | J50: oui
A51: 50 | B51: C10 | C51: Culture & Rituels | D51: Êtes-vous maître de votre calendrier de livraison (hors frozen zone) ? | E51: Formalisé 🔵 | F51: Basse | G51: Session identification des goulots résiduels : traiter un par un les derniers points de blocage et mesurer le gain d'autonomie | H51: ok | I51: V5 · Maîtrise du calendrier de livraison | J51: oui
A52: 51 | B52: D01 | C52: Toolchain CI/CD | D52: La squad est-elle en capacité de livrer en production plusieurs fois par semaine ? | E52: Initial 🔴 | F52: Haute | G52: Atelier "Notre premier pipeline" : accompagner la squad à créer son premier déclencheur automatique sur merge dans main, même sans déploiement encore | H52: ok | I52: V2 · CI : premier pipeline & .gitlab-ci.yml | J52: oui | K52: 💊 Créer une pipeline de A à Z
A53: 52 | B53: D01 | C53: Toolchain CI/CD | D53: La squad est-elle en capacité de livrer en production plusieurs fois par semaine ? | E53: Initial 🔴 | F53: Haute | G53: Session découverte de la CI/CD modulaire : présenter les templates disponibles et choisir ensemble le point de départ | H53: ok | I53: V2 · CI : premier pipeline & .gitlab-ci.yml | J53: oui | K53: notre pipeline donc les docs
A54: 53 | B54: D01 | C54: Toolchain CI/CD | D54: La squad est-elle en capacité de livrer en production plusieurs fois par semaine ? | E54: En Progrès 🟡 | F54: Moyenne | G54: Session automatisation du déploiement : accompagner l'ajout de l'étape deploy dans le pipeline existant, avec un gate manuel au début si besoin | H54: ok | I54: V2 · CI : premier pipeline & .gitlab-ci.yml | J54: oui | K54: notre pipeline donc les docs
A55: 54 | B55: D01 | C55: Toolchain CI/CD | D55: La squad est-elle en capacité de livrer en production plusieurs fois par semaine ? | E55: En Progrès 🟡 | F55: Moyenne | G55: Atelier feature flags : introduire le découplage déploiement/activation pour lever la peur de déployer souvent | H55: ↔ Chevauchement — Atelier feature flags identique à P01 (105-106). À fusionner ou simplement renvoyer vers P01 plutôt que dupliquer le contenu. | I55: V4 · Feature flags (mise en place) | J55: oui | K55: capsule mis a our
A56: 55 | B56: D01 | C56: Toolchain CI/CD | D56: La squad est-elle en capacité de livrer en production plusieurs fois par semaine ? | E56: Formalisé 🔵 | F56: Basse | G56: Atelier découpage incrémental : apprendre à slicer les fonctionnalités pour que chaque merge soit déployable indépendamment | H56: ↔ Chevauchement — Découpage/slicing pour déployabilité — sujet aussi traité en Q04 (149-150) et R04 (175-176). Le thème « petites unités » est dispersé sur 4 questions ; prévoir un atelier socle réutilisable. | I56: V2 · Kit slicing / découpage | J56: oui | K56: 💊 Users Stories Dev + Ops
A57: 56 | B57: D01 | C57: Toolchain CI/CD | D57: La squad est-elle en capacité de livrer en production plusieurs fois par semaine ? | E57: Formalisé 🔵 | F57: Basse | G57: Session "Pourquoi livrer souvent ?" : faire émerger les freins culturels et techniques qui limitent la fréquence | H57: 🔁 Mauvaise altitude : « pourquoi livrer souvent » est un atelier de niveau Initial. Au palier Formalisé, viser plutôt le trunk-based development + automatisation complète du déploiement. Intervertir avec un item Initial. | I57: V2 · CI : premier pipeline & .gitlab-ci.yml | J57: oui | K57: 💊 Créer une pipeline de A à Z
A58: 57 | B58: D02 | C58: Toolchain CI/CD | D58: Vos pipelines aboutissent-ils systématiquement sans intervention manuelle ? | E58: Initial 🔴 | F58: Haute | G58: Atelier "Autopsie de nos échecs" : catégoriser ensemble les 10 derniers échecs et identifier la cause dominante | H58: ok | I58: V3 · Stabilité du pipeline (échecs) | J58: oui
A59: 58 | B59: D02 | C59: Toolchain CI/CD | D59: Vos pipelines aboutissent-ils systématiquement sans intervention manuelle ? | E59: Initial 🔴 | F59: Haute | G59: Session stabilisation prioritaire : attaquer ensemble la catégorie d'échec la plus fréquente — tests flaky, réseau, infra | H59: ok | I59: V3 · Stabilité du pipeline (échecs) | J59: oui
A60: 59 | B60: D02 | C60: Toolchain CI/CD | D60: Vos pipelines aboutissent-ils systématiquement sans intervention manuelle ? | E60: En Progrès 🟡 | F60: Moyenne | G60: Session retry et résilience : mettre en place les retry automatiques sur les étapes réseau et les tests instables | H60: 🔁 Anti-pattern : retry sur tests flaky = on MASQUE la cause. Retry uniquement sur étapes externes (réseau, registry). Pour les tests instables : quarantaine + correction de la racine. Sinon le vert devient faux. | I60: V3 · Stabilité du pipeline (échecs) | J60: oui
A61: 60 | B61: D02 | C61: Toolchain CI/CD | D61: Vos pipelines aboutissent-ils systématiquement sans intervention manuelle ? | E61: En Progrès 🟡 | F61: Moyenne | G61: Atelier "Nos tests dans le miroir" : distinguer les vrais échecs des faux positifs et reprendre confiance dans le pipeline | H61: ok | I61: V3 · Stabilité du pipeline (échecs) | J61: oui
A62: 61 | B62: D02 | C62: Toolchain CI/CD | D62: Vos pipelines aboutissent-ils systématiquement sans intervention manuelle ? | E62: Formalisé 🔵 | F62: Basse | G62: Session monitoring de la stabilité : mettre en place une alerte si le taux de succès descend sous 90% | H62: ↔ Chevauchement — Alerte si succès < 90% = exactement S02-188 (objectif 90% KPI). Sujet stabilité dédoublé entre Toolchain (D02) et l'axe Stabilité (S). | I62: V3 · Stabilité du pipeline (échecs) | J62: oui
A63: 62 | B63: D02 | C63: Toolchain CI/CD | D63: Vos pipelines aboutissent-ils systématiquement sans intervention manuelle ? | E63: Formalisé 🔵 | F63: Basse | G63: Atelier optimisation : identifier et éliminer les dernières causes d'échec intermittent | H63: ok | I63: V3 · Stabilité du pipeline (échecs) | J63: oui
A64: 63 | B64: D03 | C64: Toolchain CI/CD | D64: Les déploiements passent-ils systématiquement par la branche principale ? | E64: Initial 🔴 | F64: Haute | G64: Session "Pourquoi main ?" : faire comprendre ensemble les risques et configurer immédiatement la restriction à main dans le .gitlab-ci.yml | H64: ok | I64: V3 · Déploiement via main & branches | J64: oui
A65: 64 | B65: D03 | C65: Toolchain CI/CD | D65: Les déploiements passent-ils systématiquement par la branche principale ? | E65: Initial 🔴 | F65: Haute | G65: Atelier gouvernance des branches : co-construire les règles de nommage et de cycle de vie adaptées à la squad | H65: ok | I65: V3 · Déploiement via main & branches | J65: oui
A66: 65 | B66: D03 | C66: Toolchain CI/CD | D66: Les déploiements passent-ils systématiquement par la branche principale ? | E66: En Progrès 🟡 | F66: Moyenne | G66: Session formalisation des exceptions : documenter ensemble les cas légitimes (hotfix, release) et créer un process pour chacun | H66: ok | I66: V3 · Déploiement via main & branches | J66: oui
A67: 66 | B67: D03 | C67: Toolchain CI/CD | D67: Les déploiements passent-ils systématiquement par la branche principale ? | E67: En Progrès 🟡 | F67: Moyenne | G67: Atelier "Nos déploiements hors main" : identifier pourquoi les exceptions existent et les éliminer une par une | H67: ok | I67: V3 · Déploiement via main & branches | J67: oui
A68: 67 | B68: D03 | C68: Toolchain CI/CD | D68: Les déploiements passent-ils systématiquement par la branche principale ? | E68: Formalisé 🔵 | F68: Basse | G68: Session automatisation de la vérification : configurer le pipeline pour refuser de s'exécuter hors main automatiquement | H68: ok | I68: V3 · Déploiement via main & branches | J68: non
A69: 68 | B69: D04 | C69: Toolchain CI/CD | D69: Utilisez-vous un système de versioning avec des releases taguées ? | E69: Initial 🔴 | F69: Haute | G69: Atelier "Notre première release" : créer ensemble le premier tag et la première release GitLab, poser les bases du semantic versioning | H69: ok | I69: V4 · Versioning & releases taguées | J69: non
... A73: 72 | B73: D04 | C73: Toolchain CI/CD | D73: Utilisez-vous un système de versioning avec des releases taguées ? | E73: Formalisé 🔵 | F73: Basse | G73: Session automatisation du changelog : mettre en place la génération automatique du changelog depuis les commits ou titres de MR | H73: ⚠ Doublon — Génération auto du changelog = action H04-98 quasi mot pour mot. Choisir un seul axe porteur (plutôt D04, c'est de la toolchain). | I73: V4 · Versioning & releases taguées | J73: non
A74: 73 | B74: D05 | C74: Toolchain CI/CD | D74: Votre pipeline complet s'exécute-t-il en moins de 15 minutes ? | E74: Initial 🔴 | F74: Haute | G74: Atelier "Anatomie de notre pipeline" : mesurer ensemble la durée de chaque stage et identifier le goulot principal | H74: ok | I74: V2 · Performance pipeline (cache, parallélisation) | J74: oui | K74: 💊 Utilisation des caches dans GitLab CI/CD
A75: 74 | B75: D05 | C75: Toolchain CI/CD | D75: Votre pipeline complet s'exécute-t-il en moins de 15 minutes ? | E75: Initial 🔴 | F75: Haute | G75: Session cache des dépendances : mettre en place le cache node_modules/.m2/pip — souvent 5 à 10 min de gagnées immédiatement | H75: ok | I75: V2 · Performance pipeline (cache, parallélisation) | J75: oui | K75: 💊 Utilisation des caches dans GitLab CI/CD
A76: 75 | B76: D05 | C76: Toolchain CI/CD | D76: Votre pipeline complet s'exécute-t-il en moins de 15 minutes ? | E76: En Progrès 🟡 | F76: Moyenne | G76: Session parallélisation : identifier les stages indépendants et les faire tourner en parallèle | H76: ok | I76: V2 · Performance pipeline (cache, parallélisation) | J76: oui | K76: 💊 Utilisation des caches dans GitLab CI/CD
A77: 76 | B77: D05 | C77: Toolchain CI/CD | D77: Votre pipeline complet s'exécute-t-il en moins de 15 minutes ? | E77: En Progrès 🟡 | F77: Moyenne | G77: Atelier optimisation Docker : réduire l'empreinte des images — multi-stage build, images slim, layers cachées | H77: ok | I77: V2 · Performance pipeline (cache, parallélisation) | J77: oui | K77: 💊 Utilisation des caches dans GitLab CI/CD
A78: 77 | B78: D05 | C78: Toolchain CI/CD | D78: Votre pipeline complet s'exécute-t-il en moins de 15 minutes ? | E78: Formalisé 🔵 | F78: Basse | G78: Session quality gates : ancrer les seuils de durée dans le pipeline et alerter si ça dérive | H78: ok | I78: V2 · Performance pipeline (cache, parallélisation) | J78: oui | K78: 💊 Utilisation des caches dans GitLab CI/CD
A79: 78 | B79: D05 | C79: Toolchain CI/CD | D79: Votre pipeline complet s'exécute-t-il en moins de 15 minutes ? | E79: Formalisé 🔵 | F79: Basse | G79: Session mise en place des indicateurs : suivre la durée dans le temps et célébrer les progrès avec la squad | H79: ok | I79: V2 · Performance pipeline (cache, parallélisation) | J79: oui | K79: 💊 Utilisation des caches dans GitLab CI/CD
A80: 79 | B80: H01 | C80: Hygiène & Gouvernance | D80: Les branches mergées ou abandonnées sont-elles supprimées régulièrement ? | E80: — | F80: Préalable | G80: Session diagnostic de l'état du repo : parcourir ensemble l'état des branches, fichiers et settings, faire émerger ce qui freine ou inquiète l'équipe | H80: ok | I80: V2 · Kit diagnostic & miroir | J80: potentiellement | K80: 💊 Documenter votre flow Git
A81: 80 | B81: H01 | C81: Hygiène & Gouvernance | D81: Les branches mergées ou abandonnées sont-elles supprimées régulièrement ? | E81: Initial 🔴 | F81: Haute | G81: Session activation de la suppression automatique : configurer ensemble la suppression de la branche source après merge | H81: 🔀 Type — Activation suppression auto = clic dans les settings. Plutôt Quick-win/Setup qu'Atelier. | I81: V3 · Hygiène des branches | J81: potentiellement | K81: 💊 Documenter votre flow Git
A82: 81 | B82: H01 | C82: Hygiène & Gouvernance | D82: Les branches mergées ou abandonnées sont-elles supprimées régulièrement ? | E82: Initial 🔴 | F82: Haute | G82: Atelier nettoyage one-shot : passer ensemble en revue toutes les branches et décider — merge, fermer ou garder | H82: ok | I82: V3 · Hygiène des branches | J82: potentiellement | K82: 💊 Documenter votre flow Git
A83: 82 | B83: H01 | C83: Hygiène & Gouvernance | D83: Les branches mergées ou abandonnées sont-elles supprimées régulièrement ? | E83: En Progrès 🟡 | F83: Moyenne | G83: Session nettoyage de l'existant : accompagner la squad à supprimer toutes les branches sans commit depuis 30+ jours | H83: ok | I83: V3 · Hygiène des branches | J83: potentiellement | K83: 💊 Documenter votre flow Git
A84: 83 | B84: H01 | C84: Hygiène & Gouvernance | D84: Les branches mergées ou abandonnées sont-elles supprimées régulièrement ? | E84: En Progrès 🟡 | F84: Moyenne | G84: Atelier conventions de nommage : co-construire des règles de nommage pour identifier rapidement les branches à nettoyer | H84: ok | I84: V3 · Hygiène des branches | J84: potentiellement | K84: 💊 Documenter votre flow Git
A85: 84 | B85: H01 | C85: Hygiène & Gouvernance | D85: Les branches mergées ou abandonnées sont-elles supprimées régulièrement ? | E85: Formalisé 🔵 | F85: Basse | G85: Session automatisation des alertes : mettre en place un job hebdomadaire qui liste les branches stale et notifie les auteurs | H85: ok | I85: V3 · Hygiène des branches | J85: potentiellement | K85: 💊 Documenter votre flow Git
A86: 85 | B86: H02 | C86: Hygiène & Gouvernance | D86: Les fichiers de lock de dépendances sont-ils versionnés ? | E86: Initial 🔴 | F86: Haute | G86: Session "Pourquoi les lock files ?" : sensibiliser ensemble aux risques des builds non reproductibles | H86: ok | I86: V4 · Lock files & mises à jour deps | J86: non
A87: 86 | B87: H02 | C87: Hygiène & Gouvernance | D87: Les fichiers de lock de dépendances sont-ils versionnés ? | E87: Initial 🔴 | F87: Haute | G87: Atelier mise en place des lock files : accompagner la squad à générer et commiter les lock files pour chaque écosystème | H87: ok | I87: V4 · Lock files & mises à jour deps | J87: non
A88: 87 | B88: H02 | C88: Hygiène & Gouvernance | D88: Les fichiers de lock de dépendances sont-ils versionnés ? | E88: En Progrès 🟡 | F88: Moyenne | G88: Session audit des écosystèmes : vérifier ensemble chaque écosystème — Node, Python, Java, Go — et compléter les manquants | H88: ok | I88: V4 · Lock files & mises à jour deps | J88: non
A89: 88 | B89: H02 | C89: Hygiène & Gouvernance | D89: Les fichiers de lock de dépendances sont-ils versionnés ? | E89: En Progrès 🟡 | F89: Moyenne | G89: Atelier .gitignore : vérifier que les lock files ne sont pas ignorés accidentellement | H89: ok | I89: V4 · Lock files & mises à jour deps | J89: non
A90: 89 | B90: H02 | C90: Hygiène & Gouvernance | D90: Les fichiers de lock de dépendances sont-ils versionnés ? | E90: Formalisé 🔵 | F90: Basse | G90: Session Renovate/Dependabot : mettre en place les mises à jour automatiques avec MR dédiées | H90: ↔ Chevauchement — Renovate/Dependabot apparaît aussi en P03-119. Cohérent mais à croiser pour ne pas écrire deux ateliers jumeaux. | I90: V4 · Lock files & mises à jour deps | J90: non
A91: 90 | B91: H03 | C91: Hygiène & Gouvernance | D91: La branche principale est-elle protégée contre le force push ? | E91: Initial 🔴 | F91: Haute | G91: Session activation immédiate : configurer ensemble la protection dans Settings > Repository > Protected branches | H91: 🔀 Type — Configuration de la branch protection : geste express, pas un atelier. L'atelier de fond, c'est 91 (les risques du force push). | I91: V1 · Runbook GitLab hardening | J91: non
A92: 91 | B92: H03 | C92: Hygiène & Gouvernance | D92: La branche principale est-elle protégée contre le force push ? | E92: Initial 🔴 | F92: Haute | G92: Atelier "Les risques du force push" : comprendre ensemble ce qu'un force push peut détruire sur un repo de prod | H92: ok | I92: V1 · Runbook GitLab hardening | J92: non
A93: 92 | B93: H03 | C93: Hygiène & Gouvernance | D93: La branche principale est-elle protégée contre le force push ? | E93: En Progrès 🟡 | F93: Moyenne | G93: Session désactivation du force push : accompagner la squad à désactiver l'option et comprendre pourquoi c'est non négociable | H93: ok | I93: V1 · Runbook GitLab hardening | J93: non
A94: 93 | B94: H03 | C94: Hygiène & Gouvernance | D94: La branche principale est-elle protégée contre le force push ? | E94: Formalisé 🔵 | F94: Basse | G94: Session niveaux d'accès : configurer ensemble push = No one, merge = Maintainers uniquement | H94: ok | I94: V1 · Runbook GitLab hardening | J94: non
A95: 94 | B95: H04 | C95: Hygiène & Gouvernance | D95: Le repo contient-il les fichiers essentiels (README, .gitignore, CHANGELOG) ? | E95: Initial 🔴 | F95: Haute | G95: Atelier "Notre repo a une identité" : co-construire ensemble un README minimal — nom, description, comment lancer, comment contribuer | H95: ✎ Reformuler — « co-construire ensemble un README » — retirer « ensemble ». Contenu très bon. | I95: V3 · Fichiers essentiels du repo | J95: potentiellement | K95: 🖼️ Template - Documentation Git
A96: 95 | B96: H04 | C96: Hygiène & Gouvernance | D96: Le repo contient-il les fichiers essentiels (README, .gitignore, CHANGELOG) ? | E96: Initial 🔴 | F96: Haute | G96: Session .gitignore : créer ensemble un .gitignore adapté à leur stack technique | H96: ok | I96: V3 · Fichiers essentiels du repo | J96: potentiellement | K96: 🖼️ Template - Documentation Git
A97: 96 | B97: H04 | C97: Hygiène & Gouvernance | D97: Le repo contient-il les fichiers essentiels (README, .gitignore, CHANGELOG) ? | E97: En Progrès 🟡 | F97: Moyenne | G97: Atelier enrichissement du README : ajouter ensemble l'architecture, les dépendances, les contacts | H97: ok | I97: V3 · Fichiers essentiels du repo | J97: potentiellement | K97: 🖼️ Template - Documentation Git
A98: 97 | B98: H04 | C98: Hygiène & Gouvernance | D98: Le repo contient-il les fichiers essentiels (README, .gitignore, CHANGELOG) ? | E98: En Progrès 🟡 | F98: Moyenne | G98: Session CHANGELOG : créer le fichier et co-décider du processus de mise à jour à chaque release | H98: ok | I98: V3 · Fichiers essentiels du repo | J98: potentiellement | K98: 🖼️ Template - Documentation Git
A99: 98 | B99: H04 | C99: Hygiène & Gouvernance | D99: Le repo contient-il les fichiers essentiels (README, .gitignore, CHANGELOG) ? | E99: Formalisé 🔵 | F99: Basse | G99: Session automatisation du CHANGELOG : mettre en place la génération automatique depuis les commits ou MR | H99: ⚠ Doublon — Doublon avec D04-72 (changelog auto depuis commits/MR). Idem renvoi. | I99: V4 · Versioning & releases taguées | J99: non
A100: 99 | B100: H04 | C100: Hygiène & Gouvernance | D100: Le repo contient-il les fichiers essentiels (README, .gitignore, CHANGELOG) ? | E100: Formalisé 🔵 | F100: Basse | G100: Atelier CONTRIBUTING.md : co-rédiger ensemble le guide d'onboarding des nouveaux contributeurs | H100: ok | I100: V3 · Fichiers essentiels du repo | J100: potentiellement | K100: 🖼️ Template - Documentation Git
A101: 100 | B101: H05 | C101: Hygiène & Gouvernance | D101: Les merge requests ouvertes sont-elles traitées sous 7 jours ? | E101: Initial 🔴 | F101: Haute | G101: Atelier tri des MR zombies : passer ensemble en revue chaque MR ouverte et décider — merge, close ou relance | H101: ↔ Chevauchement — Question H05 (traitement < 7j) très proche de Q01 (review < 48h). Tri des MR zombies = même geste qu'en Q01. Risque de redondance entre les deux axes. | I101: V3 · Flux des MR (délais & tri) | J101: potentiellement | K101: 💊 Bonnes pratiques de Merge Requests
A102: 101 | B102: H05 | C102: Hygiène & Gouvernance | D102: Les merge requests ouvertes sont-elles traitées sous 7 jours ? | E102: Initial 🔴 | F102: Haute | G102: Session "Pourquoi nos MR s'accumulent ?" : faire émerger les vraies causes et co-construire des règles de traitement | H102: ok | I102: V3 · Flux des MR (délais & tri) | J102: potentiellement | K102: 💊 Bonnes pratiques de Merge Requests
A103: 102 | B103: H05 | C103: Hygiène & Gouvernance | D103: Les merge requests ouvertes sont-elles traitées sous 7 jours ? | E103: En Progrès 🟡 | F103: Moyenne | G103: Session rappels automatiques : configurer une notification au reviewer si une MR n'a pas de review après 3 jours | H103: ↔ Chevauchement — Rappels auto après 3j ≈ Q01-134 (notif après 24h). Aligner les seuils, sinon messages contradictoires pour la squad. | I103: V3 · Flux des MR (délais & tri) | J103: potentiellement | K103: 💊 Bonnes pratiques de Merge Requests
A104: 103 | B104: H05 | C104: Hygiène & Gouvernance | D104: Les merge requests ouvertes sont-elles traitées sous 7 jours ? | E104: En Progrès 🟡 | F104: Moyenne | G104: Atelier rituel de tri hebdomadaire : instaurer un point de 10 min en daily pour traiter les MR en attente | H104: ok | I104: V3 · Flux des MR (délais & tri) | J104: potentiellement | K104: 💊 Bonnes pratiques de Merge Requests
A105: 104 | B105: H05 | C105: Hygiène & Gouvernance | D105: Les merge requests ouvertes sont-elles traitées sous 7 jours ? | E105: Formalisé 🔵 | F105: Basse | G105: Session mesure du cycle time : mettre en place le suivi du temps moyen de l'ouverture au merge (objectif < 3 jours) | H105: ↔ Chevauchement — Mesure du cycle time < 3j recouvre toute la question Q01 (review time). Décider qui porte la métrique : H05 ou Q01. | I105: V3 · Flux des MR (délais & tri) | J105: potentiellement | K105: 💊 Bonnes pratiques de Merge Requests
...

Sheet ateliers
A1: # | B1: Vague | C1: Support à produire | D1: Description | E1: Type | F1: Lignes couvertes | G1: Questions | H1: Axe(s) | I1: À retravailler d'abord | J1: Statut | L1: Définition des types de support
A2: 1 | B2: V1 | C2: Canevas DevOps Review | D2: Trame d’animation de la DevOps Review : format, rythme, indicateurs suivis et fil des actions. But : installer le rituel récurrent où la squad pilote sa progression et où tous les autres chantiers remontent et se maintiennent. | E2: Canevas | F2: 5 | G2: C07 | H2: Culture & Rituels | I2: — | J2: À produire | L2: Canevas | M2: Trame réutilisable et structurante pour un rituel récurrent (format, déroulé, indicateurs). La squad la rejoue à chaque occurrence. Ex. DevOps Review.
A3: 2 | B3: V1 | C3: Atelier Blameless / Sécurité psy | D3: Post-mortem sans blâme sur un incident réel + ancrage de la règle « on parle du système, jamais des gens ». But : créer la sécurité psychologique sans laquelle aucune rétro, diagnostic ou remontée honnête ne tient. | E3: Atelier | F3: 5 | G3: C08 | H3: Culture & Rituels | I3: Oui | J3: À produire | L3: Atelier | M3: Session animée ponctuelle (~1 h) de montée en compétence collective / co-construction sur un sujet, avec objectif, déroulé et livrable. Format majoritaire du catalogue.
A4: 3 | B4: V1 | C4: Runbook GitLab hardening | D4: Pas-à-pas de configuration des protections GitLab : branche protégée, force push interdit, règles d’approbation (2 approbateurs, auteur/committers exclus, reset on push), pipelines-must-succeed. But : mettre les repos en conformité bancaire en un seul geste outillé. | E4: Runbook | F4: 20 | G4: H03, Q02, Q05, S04, X01, X02, X03, X04, X05 | H4: Hygiène & Gouvernance, Processus Merge, Stabilité Pipeline, Sécurité | I4: — | J4: À produire | L4: Runbook | M4: Procédure opérationnelle courte et actionnable : le pourquoi + le pas-à-pas de configuration pour un geste technique ou de conformité. Pas un atelier. Ex. hardening GitLab.
A5: 4 | B5: V2 | C5: Kit diagnostic & miroir | D5: Gabarit d’animation réutilisable pour les sessions de prise de conscience : cartographie de l’existant, visualisation des données, restitution « dans le miroir ». But : un format unique servant les 3 diagnostics préalables et tous les ateliers de prise de conscience. | E5: Kit | F5: 3 | G5: H01, Q01, R01 | H5: Hygiène & Gouvernance, Processus Merge, Résilience & Bus Factor | I5: — | J5: À produire | L5: Kit | M5: Ensemble de gabarits et supports d’animation réutilisables, transverses à plusieurs questions, mutualisés pour écrire une fois et servir partout. Ex. kit diagnostic, kit slicing.
A6: 5 | B6: V2 | C6: Kit slicing / découpage | D6: Méthode et exercices de découpage : feature slicing, un seul changement logique par MR, petits incréments quotidiens. But : socle commun pour réduire la taille des MR et fluidifier le flux et la régularité des commits. | E6: Kit | F6: 8 | G6: D01, Q04, R04 | H6: Processus Merge, Résilience & Bus Factor, Toolchain CI/CD | I6: Oui | J6: À produire
A7: 6 | B7: V2 | C7: CI : premier pipeline & .gitlab-ci.yml | D7: Création du premier .gitlab-ci.yml versionné et du premier déclencheur automatique sur merge. But : poser le prérequis technique sans lequel aucun autre chantier CI/CD n’est possible. | E7: Atelier | F7: 9 | G7: D01, P05 | H7: Pratiques DevOps, Toolchain CI/CD | I7: Oui | J7: À produire
A8: 7 | B8: V2 | C8: Performance pipeline (cache, parallélisation) | D8: Mesure de la durée par stage puis optimisation : cache des dépendances, parallélisation, images Docker légères. But : ramener le pipeline sous 15 min et créer l’adhésion par un gain visible. | E8: Atelier | F8: 6 | G8: D05 | H8: Toolchain CI/CD | I8: — | J8: À produire
A9: 8 | B9: V3 | C9: Flux des MR (délais & tri) | D9: Diagnostic du cycle de vie d’une MR, SLA de review/merge, rappels automatiques et tri des MR zombies. But : raccourcir le temps d’attente et désengorger le flux de revue. | E9: Atelier | F9: 10 | G9: H05, Q01 | H9: Hygiène & Gouvernance, Processus Merge | I9: — | J9: À produire
A10: 9 | B10: V3 | C10: Stabilité du pipeline (échecs) | D10: Autopsie des échecs, stabilisation de la cause dominante, retry ciblés, suivi du taux de succès. But : rendre le pipeline fiable et redonner confiance dans le vert. | E10: Atelier | F10: 6 | G10: D02 | H10: Toolchain CI/CD | I10: Oui | J10: À produire
A11: 10 | B11: V3 | C11: Pipeline complet : test / lint / sécu | D11: Ajout progressif des stages test, lint et sécurité (SAST, scan de dépendances) avec quality gates. But : passer d’un pipeline « build seul » à un pipeline qui protège réellement. | E11: Atelier | F11: 5 | G11: P04 | H11: Pratiques DevOps | I11: — | J11: À produire
A12: 11 | B12: V3 | C12: Déploiement via main & branches | D12: Restriction des déploiements à la branche principale, gouvernance et nommage des branches, gestion des exceptions. But : fiabiliser et tracer l’origine des déploiements. | E12: Atelier | F12: 5 | G12: D03 | H12: Toolchain CI/CD | I12: — | J12: À produire
A13: 12 | B13: V3 | C13: Hygiène des branches | D13: Suppression automatique après merge, nettoyage de l’existant, conventions de nommage, alertes branches stale. But : garder un repo lisible, sans branches mortes. | E13: Atelier | F13: 5 | G13: H01 | H13: Hygiène & Gouvernance | I13: — | J13: À produire
A14: 13 | B14: V3 | C14: Fichiers essentiels du repo | D14: Mise en place et enrichissement de README, .gitignore, CHANGELOG, CONTRIBUTING. But : donner à chaque repo une identité et faciliter l’onboarding. | E14: Atelier | F14: 5 | G14: H04 | H14: Hygiène & Gouvernance | I14: — | J14: À produire
A15: 14 | B15: V4 | C15: Feature flags (mise en place) | D15: Concept du découplage déploiement/activation, premier flag, outillage, targeting. But : déployer souvent sans peur en activant les fonctionnalités à la demande. | E15: Atelier | F15: 7 | G15: D01, P01 | H15: Pratiques DevOps, Toolchain CI/CD | I15: Oui | J15: À produire
A16: 15 | B16: V4 | C16: Feature flags (nettoyage) | D16: Inventaire des flags, suppression des zombies, dates d’expiration, automatisation du nettoyage. But : éviter l’accumulation de dette de flags. | E16: Atelier | F16: 5 | G16: P02 | H16: Pratiques DevOps | I16: — | J16: À produire
A17: 16 | B17: V4 | C17: Versions de dépendances fixées | D17: Suppression des SNAPSHOT/LATEST/ranges, fixation des versions, scan de vulnérabilités. But : garantir des builds reproductibles et maîtriser le risque supply chain. | E17: Atelier | F17: 4 | G17: P03 | H17: Pratiques DevOps | I17: — | J17: À produire
... A36: 35 | B36: V5 | C36: Maîtrise du calendrier de livraison | D36: Inventaire des contraintes, négociation de SLA externes, automatisation des validations. But : reprendre la main sur le calendrier de livraison hors frozen zone. | E36: Atelier | F36: 5 | G36: C10 | H36: Culture & Rituels | I36: — | J36: À produire
C37: TOTAL | F37: =SUM(F2:F36) -> 205

Sheet 📊 Par axe
A1: Synthèse par axe d'évaluation
A3: Axe | B3: Total actions | C3: Niveau 1 (Initial) | D3: Niveau 2 (Progrès) | E3: Niveau 3 (Formalisé) | F3: % Avancement (écrits / total)
A4: Culture & Rituels | B4: =COUNTIF('🎯 205 Actions'!C2:C206,A4) -> 50 | C4: =COUNTIFS('🎯 205 Actions'!C2:C206,A4,'🎯 205 Actions'!F2:F206,"Initial 🔴") -> 20 | D4: =COUNTIFS('🎯 205 Actions'!C2:C206,A4,'🎯 205 Actions'!F2:F206,"En Progrès 🟡") -> 20 | E4: =COUNTIFS('🎯 205 Actions'!C2:C206,A4,'🎯 205 Actions'!F2:F206,"Formalisé 🔵") -> 10 | F4: =IFERROR(COUNTIFS('🎯 205 Actions'!C2:C206,A4,'🎯 205 Actions'!K2:K206,"Écrit")/B4,0) -> 0
A5: Toolchain CI/CD | B5: =COUNTIF('🎯 205 Actions'!C2:C206,A5) -> 28 | C5: =COUNTIFS('🎯 205 Actions'!C2:C206,A5,'🎯 205 Actions'!F2:F206,"Initial 🔴") -> 10 | D5: =COUNTIFS('🎯 205 Actions'!C2:C206,A5,'🎯 205 Actions'!F2:F206,"En Progrès 🟡") -> 10 | E5: =COUNTIFS('🎯 205 Actions'!C2:C206,A5,'🎯 205 Actions'!F2:F206,"Formalisé 🔵") -> 8 | F5: =IFERROR(COUNTIFS('🎯 205 Actions'!C2:C206,A5,'🎯 205 Actions'!K2:K206,"Écrit")/B5,0) -> 0
A6: Hygiène & Gouvernance | B6: =COUNTIF('🎯 205 Actions'!C2:C206,A6) -> 26 | C6: =COUNTIFS('🎯 205 Actions'!C2:C206,A6,'🎯 205 Actions'!F2:F206,"Initial 🔴") -> 10 | D6: =COUNTIFS('🎯 205 Actions'!C2:C206,A6,'🎯 205 Actions'!F2:F206,"En Progrès 🟡") -> 9 | E6: =COUNTIFS('🎯 205 Actions'!C2:C206,A6,'🎯 205 Actions'!F2:F206,"Formalisé 🔵") -> 6 | F6: =IFERROR(COUNTIFS('🎯 205 Actions'!C2:C206,A6,'🎯 205 Actions'!K2:K206,"Écrit")/B6,0) -> 0
A7: Pratiques DevOps | B7: =COUNTIF('🎯 205 Actions'!C2:C206,A7) -> 26 | C7: =COUNTIFS('🎯 205 Actions'!C2:C206,A7,'🎯 205 Actions'!F2:F206,"Initial 🔴") -> 10 | D7: =COUNTIFS('🎯 205 Actions'!C2:C206,A7,'🎯 205 Actions'!F2:F206,"En Progrès 🟡") -> 10 | E7: =COUNTIFS('🎯 205 Actions'!C2:C206,A7,'🎯 205 Actions'!F2:F206,"Formalisé 🔵") -> 6 | F7: =IFERROR(COUNTIFS('🎯 205 Actions'!C2:C206,A7,'🎯 205 Actions'!K2:K206,"Écrit")/B7,0) -> 0
A8: Processus Merge | B8: =COUNTIF('🎯 205 Actions'!C2:C206,A8) -> 27 | C8: =COUNTIFS('🎯 205 Actions'!C2:C206,A8,'🎯 205 Actions'!F2:F206,"Initial 🔴") -> 10 | D8: =COUNTIFS('🎯 205 Actions'!C2:C206,A8,'🎯 205 Actions'!F2:F206,"En Progrès 🟡") -> 10 | E8: =COUNTIFS('🎯 205 Actions'!C2:C206,A8,'🎯 205 Actions'!F2:F206,"Formalisé 🔵") -> 6 | F8: =IFERROR(COUNTIFS('🎯 205 Actions'!C2:C206,A8,'🎯 205 Actions'!K2:K206,"Écrit")/B8,0) -> 0
A9: Résilience & Bus Factor | B9: =COUNTIF('🎯 205 Actions'!C2:C206,A9) -> 21 | C9: =COUNTIFS('🎯 205 Actions'!C2:C206,A9,'🎯 205 Actions'!F2:F206,"Initial 🔴") -> 8 | D9: =COUNTIFS('🎯 205 Actions'!C2:C206,A9,'🎯 205 Actions'!F2:F206,"En Progrès 🟡") -> 8 | E9: =COUNTIFS('🎯 205 Actions'!C2:C206,A9,'🎯 205 Actions'!F2:F206,"Formalisé 🔵") -> 4 | F9: =IFERROR(COUNTIFS('🎯 205 Actions'!C2:C206,A9,'🎯 205 Actions'!K2:K206,"Écrit")/B9,0) -> 0
A10: Stabilité Pipeline | B10: =COUNTIF('🎯 205 Actions'!C2:C206,A10) -> 22 | C10: =COUNTIFS('🎯 205 Actions'!C2:C206,A10,'🎯 205 Actions'!F2:F206,"Initial 🔴") -> 10 | D10: =COUNTIFS('🎯 205 Actions'!C2:C206,A10,'🎯 205 Actions'!F2:F206,"En Progrès 🟡") -> 8 | E10: =COUNTIFS('🎯 205 Actions'!C2:C206,A10,'🎯 205 Actions'!F2:F206,"Formalisé 🔵") -> 4 | F10: =IFERROR(COUNTIFS('🎯 205 Actions'!C2:C206,A10,'🎯 205 Actions'!K2:K206,"Écrit")/B10,0) -> 0
A11: Sécurité | B11: =COUNTIF('🎯 205 Actions'!C2:C206,A11) -> 5 | C11: =COUNTIFS('🎯 205 Actions'!C2:C206,A11,'🎯 205 Actions'!F2:F206,"Initial 🔴") -> 0 | D11: =COUNTIFS('🎯 205 Actions'!C2:C206,A11,'🎯 205 Actions'!F2:F206,"En Progrès 🟡") -> 0 | E11: =COUNTIFS('🎯 205 Actions'!C2:C206,A11,'🎯 205 Actions'!F2:F206,"Formalisé 🔵") -> 0 | F11: =IFERROR(COUNTIFS('🎯 205 Actions'!C2:C206,A11,'🎯 205 Actions'!K2:K206,"Écrit")/B11,0) -> 0
A12: TOTAL | B12: =SUM(B4:B11) -> 205 | C12: =SUM(C4:C11) -> 78 | D12: =SUM(D4:D11) -> 75 | E12: =SUM(E4:E11) -> 44 | F12: =IFERROR(COUNTIF('🎯 205 Actions'!K2:K206,"Écrit")/B12,0) -> 0

Sheet 🚦 Par priorité
A1: Synthèse par priorité
A3: Vue d'ensemble
A4: Priorité | B4: Nb actions | C4: Écrits | D4: % Avancement
A5: Haute | B5: =COUNTIF('🎯 205 Actions'!G2:G206,A5) -> 83 | C5: =COUNTIFS('🎯 205 Actions'!G2:G206,A5,'🎯 205 Actions'!K2:K206,"Écrit") -> 0 | D5: =IFERROR(C5/B5,0) -> 0
A6: Moyenne | B6: =COUNTIF('🎯 205 Actions'!G2:G206,A6) -> 75 | C6: =COUNTIFS('🎯 205 Actions'!G2:G206,A6,'🎯 205 Actions'!K2:K206,"Écrit") -> 0 | D6: =IFERROR(C6/B6,0) -> 0
A7: Basse | B7: =COUNTIF('🎯 205 Actions'!G2:G206,A7) -> 44 | C7: =COUNTIFS('🎯 205 Actions'!G2:G206,A7,'🎯 205 Actions'!K2:K206,"Écrit") -> 0 | D7: =IFERROR(C7/B7,0) -> 0
A8: Préalable | B8: =COUNTIF('🎯 205 Actions'!G2:G206,A8) -> 3 | C8: =COUNTIFS('🎯 205 Actions'!G2:G206,A8,'🎯 205 Actions'!K2:K206,"Écrit") -> 0 | D8: =IFERROR(C8/B8,0) -> 0
A11: Stratégie d'écriture recommandée
A12: Phase 1 (Lancement) | B12: Top 30-50 actions Haute priorité (Niveau 1) — les plus déclenchées chez LCL
A13: Phase 2 (Stabilisation) | B13: Compléter toutes les Hautes + démarrer les Moyennes (~80-100 ateliers cumulés)
A14: Phase 3 (Couverture) | B14: Compléter Moyennes + Basses — open source / contributions externes possibles
A15: Diagnostics | B15: À écrire en parallèle des Phase 1 — préalables à plusieurs actions

Sheet 📝 Backlog Phase 1
A1: Backlog Phase 1 — Top 30-50 actions à écrire en priorité
A2: À remplir avec les actions les plus déclenchées dans les évaluations LCL (data extraite du DevOps Hub).
A4: Rang | B4: # Action | C4: Question ID | D4: Axe | E4: Action | F4: Fréquence LCL (à remplir)
A5: 1 | B5: 1 | C5: C01 | D5: Culture & Rituels | E5: Atelier "Notre premier daily" : accompagner la squad à instaurer un daily standup de 15 min max avec Dev + Ops
A6: 2 | B6: 2 | C6: C01 | D6: Culture & Rituels | E6: Session "Pourquoi des rituels ?" : faire comprendre ensemble la valeur des rituels comme ciment de la collaboration
A7: 3 | B7: 6 | C7: C02 | D7: Culture & Rituels | E7: Atelier "Notre inventaire outillage" : lister ensemble tous les outils utilisés, identifier les doublons et les usages qui se chevauchent
A8: 4 | B8: 7 | C8: C02 | D8: Culture & Rituels | E8: Session "Un outil, un usage" : co-décider des conventions — quel outil pour quel usage
A9: 5 | B9: 11 | C9: C03 | D9: Culture & Rituels | E9: Atelier "Notre canal incidents" : créer ensemble un canal dédié aux incidents avec un template de communication standard
A10: 6 | B10: 12 | C10: C03 | D10: Culture & Rituels | E10: Session "Quand et comment communiquer ?" : co-construire un protocole de communication de crise adapté à la squad
A11: 7 | B11: 16 | C11: C04 | D11: Culture & Rituels | E11: Atelier RACI : co-construire ensemble une matrice RACI sur les 10 activités clés de la squad en 30 min
A12: 8 | B12: 17 | C12: C04 | D12: Culture & Rituels | E12: Session "Qui décide quoi ?" : clarifier les décisions clés — qui valide un merge, qui contacte le support N3
A13: 9 | B13: 21 | C13: C05 | D13: Culture & Rituels | E13: Atelier "Notre backlog est-il complet ?" : faire émerger ce qui manque côté technique, sécu et ops
A14: 10 | B14: 22 | C14: C05 | D14: Culture & Rituels | E14: Session négociation avec le PO : accompagner la squad à défendre un quota minimum de 20% pour le technique
A15: 11 | B15: 26 | C15: C06 | D15: Culture & Rituels | E15: Atelier cartographie des dépendances : identifier ensemble toutes les dépendances externes et les rendre visibles
A16: 12 | B16: 27 | C16: C06 | D16: Culture & Rituels | E16: Session synchro inter-squads : instaurer un point bimensuel de 15 min avec les squads dont on dépend
... A54: 50 | B54: 127 | C54: P05 | D54: Pratiques DevOps | E54: Session création du premier fichier : créer ensemble un .gitlab-ci.yml minimal avec un stage build et le commiter
